kondoo/__init__.py
kondoo/app.py
kondoo-0.1.11.dist-info/licenses/LICENSE
kondoo-0.1.11.dist-info/METADATA
kondoo-0.1.11.dist-info/WHEEL
kondoo-0.1.11.dist-info/top_level.txt
kondoo-0.1.11.dist-info/RECORD
