Metadata-Version: 2.4
Name: kondoo
Version: 0.1.11
Summary: A flexible, self-hosted RAG chatbot framework for containerized deployments.
Author-email: Luis Pereida <luis.pereida@sysadminctl.services>, Haydee Padilla <haydee.padilla@sysadminctl.services>
License-Expression: MIT
Project-URL: Homepage, https://github.com/sysadminctl-services/kondoo
Project-URL: Repository, https://github.com/sysadminctl-services/kondoo
Project-URL: Bug Tracker, https://github.com/sysadminctl-services/kondoo/issues
Keywords: chatbot,rag,llm,ollama,gemini,self-hosted,docker,podman,container,framework,python,flask,llama-index
Classifier: Development Status :: 3 - Alpha
Classifier: Intended Audience :: Developers
Classifier: Topic :: Scientific/Engineering :: Artificial Intelligence
Classifier: Topic :: Software Development :: Libraries :: Python Modules
Classifier: Topic :: Communications :: Chat
Classifier: Programming Language :: Python :: 3
Classifier: Programming Language :: Python :: 3.9
Classifier: Programming Language :: Python :: 3.10
Classifier: Programming Language :: Python :: 3.11
Classifier: Operating System :: OS Independent
Requires-Python: >=3.9
License-File: LICENSE
Requires-Dist: flask
Requires-Dist: flask-cors
Requires-Dist: python-dotenv
Requires-Dist: google-generativeai
Requires-Dist: llama-index
Requires-Dist: llama-index-llms-google-genai
Requires-Dist: llama-index-llms-openai
Requires-Dist: llama-index-llms-openai-like
Requires-Dist: llama-index-embeddings-ollama
Requires-Dist: llama-index-embeddings-huggingface
Requires-Dist: llama-index-embeddings-openai
Requires-Dist: pyyaml
Requires-Dist: gunicorn
Dynamic: license-file
